Lab6/Q1/dec3to8.v
module dec3to8(en,inp,y);
input en;
input [2:0]inp;
output reg [7:0]y;
integer i;
always@(en,inp)
	begin
		if(en==1)
			begin
			for(i=0;i<=7;i=i+1)
				begin
					if(inp == i)
					y[i] = 1;
					else
					y[i] =0;
				end
			end
		else y=8'b00000000;
	end
endmodule

Lab6/Q1/dec4to16.v
`include "dec3to8.v"
module dec4to16(inp,y);
input [3:0]inp;
output [15:0]y;
wire d;
assign d = ~inp[3];
dec3to8 one(d,inp[2:0],y[7:0]);
dec3to8 two(inp[3],inp[2:0],y[15:8]);
endmodule

Lab6/Q1/Q1.v
//b'c'd + 	a'b'd + bc

//1001
//0001
//0011
//0110
//1110
//0111
//1111
`include "dec4to16.v"
module Q1(inp, y);
input [3:0]inp;
wire [15:0]temp;
output y;
dec4to16 eh(inp,temp);
assign y = (temp[1]|temp[3]|temp[6]|temp[7]||temp[9]|temp[14]|temp[15]);
endmodule

Lab6/Q1/Q1_tb.v
`timescale 1ns/1ns
`include "Q1.v"
module Q1_tb();
reg [3:0] inp;
wire y;
Q1 q1(inp,y);
integer i;
initial
begin 
		$dumpfile("Q1_tb.vcd");
        $dumpvars(0,Q1_tb);
        for(i=0; i<16; i=i+1) 
         begin
            inp = i; #20; 
            end
        $display("Complete");
end

endmodule

Lab6/Q1/Q1_tb.vcd
$date
	Sat Oct  8 14:56:01 2022
$end
$version
	Icarus Verilog
$end
$timescale
	1ns
$end
$scope module Q1_tb $end
$var wire 1 ! y $end
$var reg 4 " inp [3:0] $end
$var integer 32 # i [31:0] $end
$scope module q1 $end
$var wire 4 $ inp [3:0] $end
$var wire 1 ! y $end
$var wire 16 % temp [15:0] $end
$scope module eh $end
$var wire 1 & d $end
$var wire 4 ' inp [3:0] $end
$var wire 16 ( y [15:0] $end
$scope module one $end
$var wire 1 & en $end
$var wire 3 ) inp [2:0] $end
$var reg 8 * y [7:0] $end
$var integer 32 + i [31:0] $end
$upscope $end
$scope module two $end
$var wire 1 , en $end
$var wire 3 - inp [2:0] $end
$var reg 8 . y [7:0] $end
$var integer 32 / i [31:0] $end
$upscope $end
$upscope $end
$upscope $end
$upscope $end
$enddefinitions $end
#0
$dumpvars
bx /
b0 .
b0 -
0,
b1000 +
b1 *
b0 )
b1 (
b0 '
1&
b1 %
b0 $
b0 #
b0 "
0!
$end
#20
1!
b10 %
b10 (
b10 *
b1000 +
b1 )
b1 -
b1 "
b1 $
b1 '
b1 #
#40
0!
b100 %
b100 (
b100 *
b1000 +
b10 )
b10 -
b10 "
b10 $
b10 '
b10 #
#60
1!
b1000 %
b1000 (
b1000 *
b1000 +
b11 )
b11 -
b11 "
b11 $
b11 '
b11 #
#80
0!
b10000 %
b10000 (
b10000 *
b1000 +
b100 )
b100 -
b100 "
b100 $
b100 '
b100 #
#100
b100000 %
b100000 (
b100000 *
b1000 +
b101 )
b101 -
b101 "
b101 $
b101 '
b101 #
#120
1!
b1000000 %
b1000000 (
b1000000 *
b1000 +
b110 )
b110 -
b110 "
b110 $
b110 '
b110 #
#140
b10000000 %
b10000000 (
b10000000 *
b1000 +
b111 )
b111 -
b111 "
b111 $
b111 '
b111 #
#160
0!
0&
b0 *
b1000 +
b100000000 %
b100000000 (
b1 .
b1000 /
b0 )
1,
b0 -
b1000 "
b1000 $
b1000 '
b1000 #
#180
1!
b1000000000 %
b1000000000 (
b10 .
b1000 /
b1 )
b1 -
b1001 "
b1001 $
b1001 '
b1001 #
#200
0!
b10000000000 %
b10000000000 (
b100 .
b1000 /
b10 )
b10 -
b1010 "
b1010 $
b1010 '
b1010 #
#220
b100000000000 %
b100000000000 (
b1000 .
b1000 /
b11 )
b11 -
b1011 "
b1011 $
b1011 '
b1011 #
#240
b1000000000000 %
b1000000000000 (
b10000 .
b1000 /
b100 )
b100 -
b1100 "
b1100 $
b1100 '
b1100 #
#260
b10000000000000 %
b10000000000000 (
b100000 .
b1000 /
b101 )
b101 -
b1101 "
b1101 $
b1101 '
b1101 #
#280
1!
b100000000000000 %
b100000000000000 (
b1000000 .
b1000 /
b110 )
b110 -
b1110 "
b1110 $
b1110 '
b1110 #
#300
b1000000000000000 %
b1000000000000000 (
b10000000 .
b1000 /
b111 )
b111 -
b1111 "
b1111 $
b1111 '
b1111 #
#320
b10000 #
