Lab5/Q3/dec2to4.v
module dec2to4(en,inp,y);
	input en;
  input [1:0]inp;
	output reg [3:0]y;
   always @(en,inp)
     begin
       if(en==1)
        case(inp)
         0: y=4'b1110;
         1: y=4'b1101;
         2: y=4'b1011;
         3: y=4'b0111;
         endcase
       else
        y=4'b1111;
     end
endmodule

Lab5/Q3/dec4to16.v
`include "dec2to4.v"
module dec4to16(inp,y);
input [3:0]inp;
output [15:0]y;
wire [3:0]w,a;
integer i;
dec2to4 one(1'b1,inp[3:2],w[3:0]);
assign a =~w;
dec2to4 two(a[0],inp[1:0],y[3:0]);
dec2to4 three(a[1],inp[1:0],y[7:4]);
dec2to4 four(a[2],inp[1:0],y[11:8]);
dec2to4 five(a[3],inp[1:0],y[15:12]);
endmodule

Lab5/Q2/dec4to16_tb.v
`timescale 1ns/1ns
`include "dec4to16.v"
module dec4to16_tb();
reg [3:0] inp;
wire [15:0]y;
dec4to16 q1(inp,y);
integer i;
initial
begin 
		$dumpfile("dec4to16_tb.vcd");
        $dumpvars(0,dec4to16_tb);
        for(i=0; i<16; i=i+1) 
         begin
            inp = i; #20; 
            end
        $display("Complete");
end

endmodule

Lab5/Q3/dec4to16_tb.vcd
$date
	Sat Oct  1 16:30:20 2022
$end
$version
	Icarus Verilog
$end
$timescale
	1ns
$end
$scope module dec4to16_tb $end
$var wire 16 ! y [15:0] $end
$var reg 4 " inp [3:0] $end
$var integer 32 # i [31:0] $end
$scope module q1 $end
$var wire 4 $ a [3:0] $end
$var wire 4 % inp [3:0] $end
$var wire 16 & y [15:0] $end
$var wire 4 ' w [3:0] $end
$scope module five $end
$var wire 1 ( en $end
$var wire 2 ) inp [1:0] $end
$var reg 4 * y [3:0] $end
$upscope $end
$scope module four $end
$var wire 1 + en $end
$var wire 2 , inp [1:0] $end
$var reg 4 - y [3:0] $end
$upscope $end
$scope module one $end
$var wire 1 . en $end
$var wire 2 / inp [1:0] $end
$var reg 4 0 y [3:0] $end
$upscope $end
$scope module three $end
$var wire 1 1 en $end
$var wire 2 2 inp [1:0] $end
$var reg 4 3 y [3:0] $end
$upscope $end
$scope module two $end
$var wire 1 4 en $end
$var wire 2 5 inp [1:0] $end
$var reg 4 6 y [3:0] $end
$upscope $end
$upscope $end
$upscope $end
$enddefinitions $end
#0
$dumpvars
b1110 6
b0 5
14
b1111 3
b0 2
01
b1110 0
b0 /
1.
b1111 -
b0 ,
0+
b1111 *
b0 )
0(
b1110 '
b1111111111111110 &
b0 %
b1 $
b0 #
b0 "
b1111111111111110 !
$end
#20
b1111111111111101 !
b1111111111111101 &
b1101 6
b1 5
b1 2
b1 ,
b1 )
b1 "
b1 %
b1 #
#40
b1111111111111011 !
b1111111111111011 &
b1011 6
b10 5
b10 2
b10 ,
b10 )
b10 "
b10 %
b10 #
#60
b1111111111110111 !
b1111111111110111 &
b111 6
b11 5
b11 2
b11 ,
b11 )
b11 "
b11 %
b11 #
#80
b1110 3
04
11
b10 $
b1101 '
b1101 0
b1111111111101111 !
b1111111111101111 &
b1111 6
b1 /
b0 5
b0 2
b0 ,
b0 )
b100 "
b100 %
b100 #
#100
b1111111111011111 !
b1111111111011111 &
b1101 3
b1 5
b1 2
b1 ,
b1 )
b101 "
b101 %
b101 #
#120
b1111111110111111 !
b1111111110111111 &
b1011 3
b10 5
b10 2
b10 ,
b10 )
b110 "
b110 %
b110 #
#140
b1111111101111111 !
b1111111101111111 &
b111 3
b11 5
b11 2
b11 ,
b11 )
b111 "
b111 %
b111 #
#160
b1110 -
01
1+
b100 $
b1011 '
b1011 0
b1111111011111111 !
b1111111011111111 &
b1111 3
b10 /
b0 5
b0 2
b0 ,
b0 )
b1000 "
b1000 %
b1000 #
#180
b1111110111111111 !
b1111110111111111 &
b1101 -
b1 5
b1 2
b1 ,
b1 )
b1001 "
b1001 %
b1001 #
#200
b1111101111111111 !
b1111101111111111 &
b1011 -
b10 5
b10 2
b10 ,
b10 )
b1010 "
b1010 %
b1010 #
#220
b1111011111111111 !
b1111011111111111 &
b111 -
b11 5
b11 2
b11 ,
b11 )
b1011 "
b1011 %
b1011 #
#240
b1110 *
0+
1(
b1000 $
b111 '
b111 0
b1110111111111111 !
b1110111111111111 &
b1111 -
b11 /
b0 5
b0 2
b0 ,
b0 )
b1100 "
b1100 %
b1100 #
#260
b1101111111111111 !
b1101111111111111 &
b1101 *
b1 5
b1 2
b1 ,
b1 )
b1101 "
b1101 %
b1101 #
#280
b1011111111111111 !
b1011111111111111 &
b1011 *
b10 5
b10 2
b10 ,
b10 )
b1110 "
b1110 %
b1110 #
#300
b111111111111111 !
b111111111111111 &
b111 *
b11 5
b11 2
b11 ,
b11 )
b1111 "
b1111 %
b1111 #
#320
b10000 #
