Lab4/Q2/Q2.v
module Q2(a,b,c,d,f);
	input a,b,c,d;
	output f;
	//assign f = ~((~a~|~b)|(~b~|d)|(~c~|~d));
	nor(na,a,a);
	nor(nb,b,b);
	nor(nc,c,c);
	nor(nd,d,d);
	nor(f1,na,nb);
	nor(f2, nb, d);
	nor(f3, nc,nd);
	nor(f,f1,f2,f3);
endmodule

Lab4/Q2/Q2_tb.v
`timescale 1ns/1ns
`include "Q2.v"
module Q2_tb();
reg a,b,c,d;
wire f;
Q2 q2(a,b,c,d,f);
initial
begin 
		$dumpfile("q2_tb.vcd");
        $dumpvars(0,Q2_tb);
        a = 0; b = 0; c = 0; d = 0;
        #20;
        a = 0; b = 0; c = 0; d = 1;
        #20;
        a = 0; b = 0; c = 1; d = 0;
        #20;
        a = 0; b = 0; c = 1; d = 1;
        #20;
        a = 0; b = 1; c = 0; d = 0;
        #20;
        a = 0; b = 1; c = 0; d = 1;
        #20;
        a = 0; b = 1; c = 1; d = 0;
        #20;
        a = 0; b = 1; c = 1; d = 1;
        #20;
        a = 1; b = 0; c = 0; d = 0;
        #20;
        a = 1; b = 0; c = 0; d = 1;
        #20;
        a = 1; b = 0; c = 1; d = 0;
        #20;
        a = 1; b = 0; c = 1; d = 1;
        #20;
        a = 1; b = 1; c = 0; d = 0;
        #20;
        a = 1; b = 1; c = 0; d = 1;
        #20;
        a = 1; b = 1; c = 1; d = 0;
        #20;
        a = 1; b = 1; c = 1; d = 1;
        #20;
        $display("Complete");
end

endmodule

Lab4/Q2/q2_tb.vcd
$date
	Sat Sep 17 15:19:20 2022
$end
$version
	Icarus Verilog
$end
$timescale
	1ns
$end
$scope module Q2_tb $end
$var wire 1 ! f $end
$var reg 1 " a $end
$var reg 1 # b $end
$var reg 1 $ c $end
$var reg 1 % d $end
$scope module q2 $end
$var wire 1 " a $end
$var wire 1 # b $end
$var wire 1 $ c $end
$var wire 1 % d $end
$var wire 1 ! f $end
$var wire 1 & f1 $end
$var wire 1 ' f2 $end
$var wire 1 ( f3 $end
$var wire 1 ) na $end
$var wire 1 * nb $end
$var wire 1 + nc $end
$var wire 1 , nd $end
$upscope $end
$upscope $end
$enddefinitions $end
#0
$dumpvars
1,
1+
1*
1)
0(
0'
0&
0%
0$
0#
0"
1!
$end
#20
0,
1%
#40
1,
0+
0%
1$
#60
0!
1(
0,
1%
#80
0(
1,
1'
1+
0*
0%
0$
1#
#100
1!
0,
0'
1%
#120
0!
1,
1'
0+
0%
1$
#140
1(
0!
0,
0'
1%
#160
1!
0(
1,
1+
1*
0)
0%
0$
0#
1"
#180
0,
1%
#200
1,
0+
0%
1$
#220
0!
1(
0,
1%
#240
0(
1&
1,
1'
1+
0*
0%
0$
1#
#260
0,
0'
1%
#280
1,
1'
0+
0%
1$
#300
1(
0,
0'
1%
