Lab1/Q1/Q1i.v
module Q1i(a,b,c,d,f);
	input a,b,c,d;
	output f;
	and(g,a,b);
	and(h,a,b);
	or(i,g,c);
	or(j,h,c);
	not(k,i);
	and(l,k,d);
	or(m,j,d);
	and(f,l,m);
endmodule

Lab1/Q1/Q1i_tb.v
`timescale 1ns/1ns
`include "Q1i.v"
module Q1i_tb();
reg a,b,c,d;
wire f;
Q1i q1i(a,b,c,d,f);
initial
begin
	$dumpfile("qi1_tb.vcd");
	$dumpvars(0,Q1i_tb);
	a = 0; b = 0; c = 0; d = 0;
	#20;
	a = 0; b = 0; c = 0; d = 1;
	#20;
	a = 0; b = 0; c = 1; d = 0;
	#20;
	a = 0; b = 0; c = 1; d = 1;
	#20;
	a = 0; b = 1; c = 0; d = 0;
	#20;
	a = 0; b = 1; c = 0; d = 1;
	#20;
	a = 0; b = 1; c = 1; d = 0;
	#20;
	a = 0; b = 1; c = 1; d = 1;
	#20;
	a = 1; b = 0; c = 0; d = 0;
	#20;
	a = 1; b = 0; c = 0; d = 1;
	#20;
	a = 1; b = 0; c = 1; d = 0;
	#20;
	a = 1; b = 0; c = 1; d = 1;
	#20;
	a = 1; b = 1; c = 0; d = 0;
	#20;
	a = 1; b = 1; c = 0; d = 1;
	#20;
	a = 1; b = 1; c = 1; d = 0;
	#20;
	a = 1; b = 1; c = 1; d = 1;
	#20;
	$display("Complete");
end

endmodule

Lab1/Q1/qi1_tb.vcd
$date
	Sat Aug 27 15:04:14 2022
$end
$version
	Icarus Verilog
$end
$timescale
	1ns
$end
$scope module Q1i_tb $end
$var wire 1 ! f $end
$var reg 1 " a $end
$var reg 1 # b $end
$var reg 1 $ c $end
$var reg 1 % d $end
$scope module q1i $end
$var wire 1 " a $end
$var wire 1 # b $end
$var wire 1 $ c $end
$var wire 1 % d $end
$var wire 1 ! f $end
$var wire 1 & g $end
$var wire 1 ' h $end
$var wire 1 ( i $end
$var wire 1 ) j $end
$var wire 1 * k $end
$var wire 1 + l $end
$var wire 1 , m $end
$upscope $end
$upscope $end
$enddefinitions $end
#0
$dumpvars
0,
0+
1*
0)
0(
0'
0&
0%
0$
0#
0"
0!
$end
#20
1!
1+
1,
1%
#40
0!
0*
0+
1(
1)
0%
1$
#60
1%
#80
1*
0,
0(
0)
0%
0$
1#
#100
1!
1+
1,
1%
#120
0!
0*
0+
1(
1)
0%
1$
#140
1%
#160
1*
0,
0(
0)
0%
0$
0#
1"
#180
1!
1+
1,
1%
#200
0!
0*
0+
1(
1)
0%
1$
#220
1%
#240
1&
1'
0%
0$
1#
#260
1%
#280
0%
1$
#300
1%
