Lab7/Q2/mux4to1.v
module mux4to1(inp, s, y);
input [3:0]inp;
input [1:0]s;
output reg y;
always@(inp,s)
 y = s[1]?s[0]?inp[3]:inp[2]:s[0]?inp[1]:inp[0];
endmodule

Lab7/Q2/Q2.v
`include "mux4to1.v"
module Q2(inp, s, y);
input [15:0]inp;
input [3:0]s;
output y;
wire [3:0]temp;
mux4to1 m1(inp[3:0],s[1:0],temp[0]);
mux4to1 m2(inp[7:4],s[1:0],temp[1]);
mux4to1 m3(inp[11:8],s[1:0],temp[2]);
mux4to1 m4(inp[15:12],s[1:0],temp[3]);
mux4to1 m5(temp[3:0],s[3:2],y);
endmodule

Lab7/Q2/Q2_tb.v
`timescale 1ns/1ns
`include "Q2.v"
module Q2_tb();
reg [15:0]inp;
reg [3:0]s;
wire y;
Q2 q2(inp,s,y);
integer i;
initial
begin 
		$dumpfile("q2.vcd");
        $dumpvars(0,q2);
        inp = 16'b1010101010101010;
        for(i=0; i<16; i=i+1) 
         begin
            s = i[3:0]; #20; 
            end
        $display("Complete");
end

endmodule

Lab7/Q2/q2.vcd
$date
	Sat Oct 22 14:31:34 2022
$end
$version
	Icarus Verilog
$end
$timescale
	1ns
$end
$scope module Q2_tb $end
$scope module q2 $end
$var wire 16 ! inp [15:0] $end
$var wire 4 " s [3:0] $end
$var wire 1 # y $end
$var wire 4 $ temp [3:0] $end
$scope module m1 $end
$var wire 4 % inp [3:0] $end
$var wire 2 & s [1:0] $end
$var reg 1 ' y $end
$upscope $end
$scope module m2 $end
$var wire 4 ( inp [3:0] $end
$var wire 2 ) s [1:0] $end
$var reg 1 * y $end
$upscope $end
$scope module m3 $end
$var wire 4 + inp [3:0] $end
$var wire 2 , s [1:0] $end
$var reg 1 - y $end
$upscope $end
$scope module m4 $end
$var wire 4 . inp [3:0] $end
$var wire 2 / s [1:0] $end
$var reg 1 0 y $end
$upscope $end
$scope module m5 $end
$var wire 4 1 inp [3:0] $end
$var wire 2 2 s [1:0] $end
$var reg 1 # y $end
$upscope $end
$upscope $end
$upscope $end
$enddefinitions $end
#0
$dumpvars
b0 2
b0 1
00
b0 /
b1010 .
0-
b0 ,
b1010 +
0*
b0 )
b1010 (
0'
b0 &
b1010 %
b0 $
0#
b0 "
b1010101010101010 !
$end
#20
1#
1'
1*
1-
b1111 $
b1111 1
10
b1 &
b1 )
b1 ,
b1 /
b1 "
#40
0#
0'
0*
0-
b0 $
b0 1
00
b10 &
b10 )
b10 ,
b10 /
b10 "
#60
1#
1'
1*
1-
b1111 $
b1111 1
10
b11 &
b11 )
b11 ,
b11 /
b11 "
#80
0#
0'
0*
0-
b0 $
b0 1
00
b0 &
b0 )
b0 ,
b0 /
b1 2
b100 "
#100
1#
1'
1*
1-
b1111 $
b1111 1
10
b1 &
b1 )
b1 ,
b1 /
b101 "
#120
0#
0'
0*
0-
b0 $
b0 1
00
b10 &
b10 )
b10 ,
b10 /
b110 "
#140
1#
1'
1*
1-
b1111 $
b1111 1
10
b11 &
b11 )
b11 ,
b11 /
b111 "
#160
0#
0'
0*
0-
b0 $
b0 1
00
b0 &
b0 )
b0 ,
b0 /
b10 2
b1000 "
#180
1#
1'
1*
1-
b1111 $
b1111 1
10
b1 &
b1 )
b1 ,
b1 /
b1001 "
#200
0#
0'
0*
0-
b0 $
b0 1
00
b10 &
b10 )
b10 ,
b10 /
b1010 "
#220
1#
1'
1*
1-
b1111 $
b1111 1
10
b11 &
b11 )
b11 ,
b11 /
b1011 "
#240
0#
0'
0*
0-
b0 $
b0 1
00
b0 &
b0 )
b0 ,
b0 /
b11 2
b1100 "
#260
1#
1'
1*
1-
b1111 $
b1111 1
10
b1 &
b1 )
b1 ,
b1 /
b1101 "
#280
0#
0'
0*
0-
b0 $
b0 1
00
b10 &
b10 )
b10 ,
b10 /
b1110 "
#300
1#
1'
1*
1-
b1111 $
b1111 1
10
b11 &
b11 )
b11 ,
b11 /
b1111 "
