Lab3/Q1/b/Q1_b.v
module Q1_b(a,b,c,d,f);
	input a,b,c,d;
	output f;
	assign f = (~b&d) | (~b&c) | (b&~c&~d);
endmodule

Lab3/Q1/b/Q1_tb.v
`timescale 1ns/1ns
`include "Q1_b.v"
module Q1_tb();
reg a,b,c,d;
wire f;
Q1_b q1_b(a,b,c,d,f);
initial
begin 
		$dumpfile("q1_tb.vcd");
        $dumpvars(0,Q1_tb);
        a = 0; b = 0; c = 0; d = 0;
        #20;
        a = 0; b = 0; c = 0; d = 1;
        #20;
        a = 0; b = 0; c = 1; d = 0;
        #20;
        a = 0; b = 0; c = 1; d = 1;
        #20;
        a = 0; b = 1; c = 0; d = 0;
        #20;
        a = 0; b = 1; c = 0; d = 1;
        #20;
        a = 0; b = 1; c = 1; d = 0;
        #20;
        a = 0; b = 1; c = 1; d = 1;
        #20;
        a = 1; b = 0; c = 0; d = 0;
        #20;
        a = 1; b = 0; c = 0; d = 1;
        #20;
        a = 1; b = 0; c = 1; d = 0;
        #20;
        a = 1; b = 0; c = 1; d = 1;
        #20;
        a = 1; b = 1; c = 0; d = 0;
        #20;
        a = 1; b = 1; c = 0; d = 1;
        #20;
        a = 1; b = 1; c = 1; d = 0;
        #20;
        a = 1; b = 1; c = 1; d = 1;
        #20;
        $display("Complete");
end

endmodule

Lab3/Q1/b/q1_tb.vcd
$date
	Sat Sep 10 14:24:29 2022
$end
$version
	Icarus Verilog
$end
$timescale
	1ns
$end
$scope module Q1_tb $end
$var wire 1 ! f $end
$var reg 1 " a $end
$var reg 1 # b $end
$var reg 1 $ c $end
$var reg 1 % d $end
$scope module q1_b $end
$var wire 1 " a $end
$var wire 1 # b $end
$var wire 1 $ c $end
$var wire 1 % d $end
$var wire 1 ! f $end
$upscope $end
$upscope $end
$enddefinitions $end
#0
$dumpvars
0%
0$
0#
0"
0!
$end
#20
1!
1%
#40
0%
1$
#60
1%
#80
0%
0$
1#
#100
0!
1%
#120
0%
1$
#140
1%
#160
0%
0$
0#
1"
#180
1!
1%
#200
0%
1$
#220
1%
#240
0%
0$
1#
#260
0!
1%
#280
0%
1$
#300
1%
