Lab6/Q2/dec2to4.v
module dec2to4(en,inp,y);
	input en;
  input [1:0]inp;
	output reg [3:0]y;
   always @(en,inp)
     begin
       if(en==1)
        case(inp)
         0: y=4'b0001;
         1: y=4'b0010;
         2: y=4'b0100;
         3: y=4'b1000;
         endcase
       else
        y=4'b0000;
     end
endmodule

Lab6/Q2/dec4to16.v
`include "dec2to4.v"
module dec4to16(inp,y);
input [3:0]inp;
output  [15:0]y;
wire [3:0]w;
integer i;
dec2to4 one(1'b1,inp[3:2],w[3:0]);
dec2to4 two(w[0],inp[1:0],y[3:0]);
dec2to4 three(w[1],inp[1:0],y[7:4]);
dec2to4 four(w[2],inp[1:0],y[11:8]);
dec2to4 five(w[3],inp[1:0],y[15:12]);
endmodule

Lab6/Q2/Q2.v
//F = 101x + 0x11 + x110  == 10 11 3 7 6 14
//G = 1x10 + 001x == 10 14 2 3
//H = 000x + 111x + 0x11 ==  0 1 14 15 3 7
`include "dec4to16.v"
module Q2(inp, f, g, h, temp);
input [3:0]inp;
output [15:0]temp;
output f,g,h;
dec4to16 why(inp, temp);
assign f = (temp[10]|temp[11]|temp[3]|temp[7]|temp[6]|temp[14] );
assign g = (temp[2]|temp[3]|temp[10]|temp[14]);	
assign h = (temp[0]|temp[1]|temp[3]|temp[7]|temp[14]|temp[15]);
endmodule

Lab6/Q2/Q2_tb.v
`timescale 1ns/1ns
`include "Q2.v"
module Q2_tb();
reg [3:0] inp;
wire f,g,h;
wire [15:0]temp;
Q2 q(inp,f,g,h, temp);
integer i;
initial
begin 
		$dumpfile("Q2_tb.vcd");
        $dumpvars(0,Q2_tb);
        for(i=0; i<16; i=i+1) 
         begin
            inp = i; #20; 
            end
        $display("Complete");
end

endmodule

Lab6/Q2/Q2_tb.vcd
$date
	Sat Oct  8 15:36:28 2022
$end
$version
	Icarus Verilog
$end
$timescale
	1ns
$end
$scope module Q2_tb $end
$var wire 16 ! temp [15:0] $end
$var wire 1 " h $end
$var wire 1 # g $end
$var wire 1 $ f $end
$var reg 4 % inp [3:0] $end
$var integer 32 & i [31:0] $end
$scope module q $end
$var wire 1 $ f $end
$var wire 1 # g $end
$var wire 1 " h $end
$var wire 4 ' inp [3:0] $end
$var wire 16 ( temp [15:0] $end
$scope module why $end
$var wire 4 ) inp [3:0] $end
$var wire 16 * y [15:0] $end
$var wire 4 + w [3:0] $end
$scope module five $end
$var wire 1 , en $end
$var wire 2 - inp [1:0] $end
$var reg 4 . y [3:0] $end
$upscope $end
$scope module four $end
$var wire 1 / en $end
$var wire 2 0 inp [1:0] $end
$var reg 4 1 y [3:0] $end
$upscope $end
$scope module one $end
$var wire 1 2 en $end
$var wire 2 3 inp [1:0] $end
$var reg 4 4 y [3:0] $end
$upscope $end
$scope module three $end
$var wire 1 5 en $end
$var wire 2 6 inp [1:0] $end
$var reg 4 7 y [3:0] $end
$upscope $end
$scope module two $end
$var wire 1 8 en $end
$var wire 2 9 inp [1:0] $end
$var reg 4 : y [3:0] $end
$upscope $end
$upscope $end
$upscope $end
$upscope $end
$enddefinitions $end
#0
$dumpvars
b1 :
b0 9
18
b0 7
b0 6
05
b1 4
b0 3
12
b0 1
b0 0
0/
b0 .
b0 -
0,
b1 +
b1 *
b0 )
b1 (
b0 '
b0 &
b0 %
0$
0#
1"
b1 !
$end
#20
b10 !
b10 (
b10 *
b10 :
b1 9
b1 6
b1 0
b1 -
b1 %
b1 '
b1 )
b1 &
#40
0"
1#
b100 !
b100 (
b100 *
b100 :
b10 9
b10 6
b10 0
b10 -
b10 %
b10 '
b10 )
b10 &
#60
1"
1$
b1000 !
b1000 (
b1000 *
b1000 :
b11 9
b11 6
b11 0
b11 -
b11 %
b11 '
b11 )
b11 &
#80
0"
0$
0#
b1 7
15
08
b10 +
b10 4
b10000 !
b10000 (
b10000 *
b0 :
b1 3
b0 9
b0 6
b0 0
b0 -
b100 %
b100 '
b100 )
b100 &
#100
b100000 !
b100000 (
b100000 *
b10 7
b1 9
b1 6
b1 0
b1 -
b101 %
b101 '
b101 )
b101 &
#120
1$
b1000000 !
b1000000 (
b1000000 *
b100 7
b10 9
b10 6
b10 0
b10 -
b110 %
b110 '
b110 )
b110 &
#140
1"
b10000000 !
b10000000 (
b10000000 *
b1000 7
b11 9
b11 6
b11 0
b11 -
b111 %
b111 '
b111 )
b111 &
#160
0"
0$
b1 1
1/
05
b100 +
b100 4
b100000000 !
b100000000 (
b100000000 *
b0 7
b10 3
b0 9
b0 6
b0 0
b0 -
b1000 %
b1000 '
b1000 )
b1000 &
#180
b1000000000 !
b1000000000 (
b1000000000 *
b10 1
b1 9
b1 6
b1 0
b1 -
b1001 %
b1001 '
b1001 )
b1001 &
#200
1$
1#
b10000000000 !
b10000000000 (
b10000000000 *
b100 1
b10 9
b10 6
b10 0
b10 -
b1010 %
b1010 '
b1010 )
b1010 &
#220
0#
b100000000000 !
b100000000000 (
b100000000000 *
b1000 1
b11 9
b11 6
b11 0
b11 -
b1011 %
b1011 '
b1011 )
b1011 &
#240
0$
b1 .
1,
0/
b1000 +
b1000 4
b1000000000000 !
b1000000000000 (
b1000000000000 *
b0 1
b11 3
b0 9
b0 6
b0 0
b0 -
b1100 %
b1100 '
b1100 )
b1100 &
#260
b10000000000000 !
b10000000000000 (
b10000000000000 *
b10 .
b1 9
b1 6
b1 0
b1 -
b1101 %
b1101 '
b1101 )
b1101 &
#280
1"
1#
1$
b100000000000000 !
b100000000000000 (
b100000000000000 *
b100 .
b10 9
b10 6
b10 0
b10 -
b1110 %
b1110 '
b1110 )
b1110 &
#300
0#
0$
b1000000000000000 !
b1000000000000000 (
b1000000000000000 *
b1000 .
b11 9
b11 6
b11 0
b11 -
b1111 %
b1111 '
b1111 )
b1111 &
#320
b10000 &
