Lab4/Q1/Q1.v
module Q1 (a,b,c,d,f);
	input a,b,c,d;
	output f;
	//assign f = ~((~a~&~c)&(~a~&d)&(~c~&b)&(b~&d));
	nand(na,a,a);
	nand(nb,b,b);
	nand(nc,c,c);
	nand(f1,na,nc);
	nand(f2, na,d);
	nand(f3, nc,b);
	nand(f4,b,d);
	nand(f,f1,f2,f3,f4);
endmodule

Lab4/Q1/Q1_tb.v
`timescale 1ns/1ns
`include "Q1.v"
module Q1_tb();
reg a,b,c,d;
wire f;
Q1 q1(a,b,c,d,f);
initial
begin 
		$dumpfile("q1_tb.vcd");
        $dumpvars(0,Q1_tb);
        a = 0; b = 0; c = 0; d = 0;
        #20;
        a = 0; b = 0; c = 0; d = 1;
        #20;
        a = 0; b = 0; c = 1; d = 0;
        #20;
        a = 0; b = 0; c = 1; d = 1;
        #20;
        a = 0; b = 1; c = 0; d = 0;
        #20;
        a = 0; b = 1; c = 0; d = 1;
        #20;
        a = 0; b = 1; c = 1; d = 0;
        #20;
        a = 0; b = 1; c = 1; d = 1;
        #20;
        a = 1; b = 0; c = 0; d = 0;
        #20;
        a = 1; b = 0; c = 0; d = 1;
        #20;
        a = 1; b = 0; c = 1; d = 0;
        #20;
        a = 1; b = 0; c = 1; d = 1;
        #20;
        a = 1; b = 1; c = 0; d = 0;
        #20;
        a = 1; b = 1; c = 0; d = 1;
        #20;
        a = 1; b = 1; c = 1; d = 0;
        #20;
        a = 1; b = 1; c = 1; d = 1;
        #20;
        $display("Complete");
end

endmodule

Lab4/Q1/q1_tb.vcd
$date
	Sat Sep 17 15:18:09 2022
$end
$version
	Icarus Verilog
$end
$timescale
	1ns
$end
$scope module Q1_tb $end
$var wire 1 ! f $end
$var reg 1 " a $end
$var reg 1 # b $end
$var reg 1 $ c $end
$var reg 1 % d $end
$scope module q1 $end
$var wire 1 " a $end
$var wire 1 # b $end
$var wire 1 $ c $end
$var wire 1 % d $end
$var wire 1 ! f $end
$var wire 1 & f1 $end
$var wire 1 ' f2 $end
$var wire 1 ( f3 $end
$var wire 1 ) f4 $end
$var wire 1 * na $end
$var wire 1 + nb $end
$var wire 1 , nc $end
$upscope $end
$upscope $end
$enddefinitions $end
#0
$dumpvars
1,
1+
1*
1)
1(
1'
0&
0%
0$
0#
0"
1!
$end
#20
0'
1%
#40
0!
1&
1'
0,
0%
1$
#60
1!
0'
1%
#80
0&
0(
1'
1,
0+
0%
0$
1#
#100
0'
0)
1%
#120
0!
1&
1(
1'
1)
0,
0%
1$
#140
1!
0'
0)
1%
#160
0!
1'
1,
1+
1)
0*
0%
0$
0#
1"
#180
1%
#200
0,
0%
1$
#220
1%
#240
1!
0(
1,
0+
0%
0$
1#
#260
0)
1%
#280
0!
1(
1)
0,
0%
1$
#300
1!
0)
1%
