Lab7/Q1/mux2to1.v
module mux2to1(inp, s, y);
input [1:0]inp;
input s;
output reg y;
always@(inp,s)
 begin
	if(s==0)
		y = inp[0];
	if(s==1)
		y = inp[1];
 end
endmodule

Lab7/Q3/mux8to1.v
module mux8to1(inp, s, y);
input [7:0]inp;
input [2:0]s;
output reg y;
always@(inp,s)
 begin
	case(s)
	 0: y = inp[0];
	 1: y = inp[1];
	 2: y = inp[2];
	 3: y = inp[3];
	 4: y = inp[4];
	 5: y = inp[5];
	 6: y = inp[6];
	 7: y = inp[7];
	 endcase
 end
endmodule

Lab7/Q3/Q3.v
`include "mux2to1.v"
`include "mux8to1.v"
module Q3(inp, s, y);
input [15:0]inp;
input [3:0]s;
output y;
wire [1:0]temp;
mux8to1 m1(inp[7:0],s[2:0],temp[0]);
mux8to1 m2(inp[15:8],s[2:0],temp[1]);
mux2to1 m3(temp[1:0],s[3],y);
endmodule

Lab7/Q3/Q3_tb.v
`timescale 1ns/1ns
`include "Q3.v"
module Q2_tb();
reg [15:0]inp;
reg [3:0]s;
wire y;
Q3 q3(inp,s,y);
integer i;
initial
begin 
		$dumpfile("q3.vcd");
        $dumpvars(0,q3);
        inp = 16'b1010101010101010;
        for(i=0; i<16; i=i+1) 
         begin
            s = i[3:0]; #20; 
            end
        $display("Complete");
end

endmodule

Lab7/Q3/q3.vcd
$date
	Sat Oct 22 14:43:04 2022
$end
$version
	Icarus Verilog
$end
$timescale
	1ns
$end
$scope module Q2_tb $end
$scope module q3 $end
$var wire 16 ! inp [15:0] $end
$var wire 4 " s [3:0] $end
$var wire 1 # y $end
$var wire 2 $ temp [1:0] $end
$scope module m1 $end
$var wire 8 % inp [7:0] $end
$var wire 3 & s [2:0] $end
$var reg 1 ' y $end
$upscope $end
$scope module m2 $end
$var wire 8 ( inp [7:0] $end
$var wire 3 ) s [2:0] $end
$var reg 1 * y $end
$upscope $end
$scope module m3 $end
$var wire 2 + inp [1:0] $end
$var wire 1 , s $end
$var reg 1 # y $end
$upscope $end
$upscope $end
$upscope $end
$enddefinitions $end
#0
$dumpvars
0,
b0 +
0*
b0 )
b10101010 (
0'
b0 &
b10101010 %
b0 $
0#
b0 "
b1010101010101010 !
$end
#20
1#
1'
b11 $
b11 +
1*
b1 &
b1 )
b1 "
#40
0#
0'
b0 $
b0 +
0*
b10 &
b10 )
b10 "
#60
1#
1'
b11 $
b11 +
1*
b11 &
b11 )
b11 "
#80
0#
0'
b0 $
b0 +
0*
b100 &
b100 )
b100 "
#100
1#
1'
b11 $
b11 +
1*
b101 &
b101 )
b101 "
#120
0#
0'
b0 $
b0 +
0*
b110 &
b110 )
b110 "
#140
1#
1'
b11 $
b11 +
1*
b111 &
b111 )
b111 "
#160
0#
0'
b0 $
b0 +
0*
b0 &
b0 )
1,
b1000 "
#180
1#
1'
b11 $
b11 +
1*
b1 &
b1 )
b1001 "
#200
0#
0'
b0 $
b0 +
0*
b10 &
b10 )
b1010 "
#220
1#
1'
b11 $
b11 +
1*
b11 &
b11 )
b1011 "
#240
0#
0'
b0 $
b0 +
0*
b100 &
b100 )
b1100 "
#260
1#
1'
b11 $
b11 +
1*
b101 &
b101 )
b1101 "
#280
0#
0'
b0 $
b0 +
0*
b110 &
b110 )
b1110 "
#300
1#
1'
b11 $
b11 +
1*
b111 &
b111 )
b1111 "
