Lab1/Q2/Q2ii.v
module Q2ii(a,b,c,d,g,f);
	input a,b,c,d;
	output g,f;
	assign g = ~(b|c|d);
	assign f = (~(a&b))^c^d;
endmodule

Lab1/Q2/Q2ii_tb.v
`timescale 1ns/1ns
`include "Q2ii.v"
module Q2ii_tb();
reg a,b,c,d;
wire f;
Q2ii q2ii(a,b,c,d,g,f);
initial
begin
        $dumpfile("q2ii_tb.vcd");
        $dumpvars(0,Q2ii_tb);
        a = 0; b = 0; c = 0; d = 0;
        #20;
        a = 0; b = 0; c = 0; d = 1;
        #20;
        a = 0; b = 0; c = 1; d = 0;
        #20;
        a = 0; b = 0; c = 1; d = 1;
        #20;
        a = 0; b = 1; c = 0; d = 0;
        #20;
        a = 0; b = 1; c = 0; d = 1;
        #20;
        a = 0; b = 1; c = 1; d = 0;
        #20;
        a = 0; b = 1; c = 1; d = 1;
        #20;
        a = 1; b = 0; c = 0; d = 0;
        #20;
        a = 1; b = 0; c = 0; d = 1;
        #20;
        a = 1; b = 0; c = 1; d = 0;
        #20;
        a = 1; b = 0; c = 1; d = 1;
        #20;
        a = 1; b = 1; c = 0; d = 0;
        #20;
        a = 1; b = 1; c = 0; d = 1;
        #20;
        a = 1; b = 1; c = 1; d = 0;
        #20;
        a = 1; b = 1; c = 1; d = 1;
        #20;
        $display("Complete");
end

endmodule

Lab1/Q2/q2ii_tb.vcd
$date
	Sat Aug 27 15:42:16 2022
$end
$version
	Icarus Verilog
$end
$timescale
	1ns
$end
$scope module Q2ii_tb $end
$var wire 1 ! g $end
$var wire 1 " f $end
$var reg 1 # a $end
$var reg 1 $ b $end
$var reg 1 % c $end
$var reg 1 & d $end
$scope module q2ii $end
$var wire 1 # a $end
$var wire 1 $ b $end
$var wire 1 % c $end
$var wire 1 & d $end
$var wire 1 " f $end
$var wire 1 ! g $end
$upscope $end
$upscope $end
$enddefinitions $end
#0
$dumpvars
0&
0%
0$
0#
1"
1!
$end
#20
0!
0"
1&
#40
0&
1%
#60
1"
1&
#80
0&
0%
1$
#100
0"
1&
#120
0&
1%
#140
1"
1&
#160
1!
0&
0%
0$
1#
#180
0!
0"
1&
#200
0&
1%
#220
1"
1&
#240
0"
0&
0%
1$
#260
1"
1&
#280
0&
1%
#300
0"
1&
