Lab1/Additional/Ai.v
module Ai(a,b,c,f1,f2);
	input  a,b,c;
	output  f1,f2;
	assign f1 = (a&~c)|(b&c)|(~b&~c);
	assign f2 = (a|~b|c)&(a|b|~c)&(~a|b|~c);
endmodule

Lab1/Additional/Ai_tb.v
`timescale 1ns/1ns
`include "Ai.v"
module Ai_tb();
reg a,b,c;
wire f1,f2;
Ai Ai(a,b,c,f1,f2);
initial
begin
        $dumpfile("Ai_tb.vcd");
        $dumpvars(0,Ai_tb);
        a = 0; b = 0; c = 0;
        #20;
        a = 0; b = 0; c = 1;
        #20;
	a = 0; b = 1; c = 0;
	#20;
        a = 0; b = 1; c = 1;
        #20;
        a = 1; b = 0; c = 0;
        #20;
        a = 1; b = 0; c = 1;
        #20;
        a = 1; b = 1; c = 0;
	#20;
        a = 1; b = 1; c = 1;
        #20;
        $display(((f1&f2==f1) &(f1&~f2==0) )?"Equivalent":"Not Equivalent");
end

endmodule

Lab1/Additional/Ai_tb.vcd
$date
	Sat Aug 27 16:20:59 2022
$end
$version
	Icarus Verilog
$end
$timescale
	1ns
$end
$scope module Ai_tb $end
$var wire 1 ! f2 $end
$var wire 1 " f1 $end
$var reg 1 # a $end
$var reg 1 $ b $end
$var reg 1 % c $end
$scope module Ai $end
$var wire 1 # a $end
$var wire 1 $ b $end
$var wire 1 % c $end
$var wire 1 " f1 $end
$var wire 1 ! f2 $end
$upscope $end
$upscope $end
$enddefinitions $end
#0
$dumpvars
0%
0$
0#
1"
1!
$end
#20
0!
0"
1%
#40
0!
0%
1$
#60
1"
1!
1%
#80
0%
0$
1#
#100
0"
0!
1%
#120
1"
1!
0%
1$
#140
1%
