Lab4/Q4/Q4.v
module Q4(a,b,c,d,f);
	input a,b,c,d;
	output f;
	//assign f = 	(~a~|~c)~|~d;
	nor(na,a,a);
	nor(nc,c,c);
	nor(nd,d,d);
	nor(f1, na, nc);
	nor(f,f1,nd);
endmodule

Lab4/Q4/Q4_tb.v
`timescale 1ns/1ns
`include "Q4.v"
module Q4_tb();
reg a,b,c,d;
wire f;
Q4 q4(a,b,c,d,f);
initial
begin 
		$dumpfile("q4_tb.vcd");
        $dumpvars(0,Q4_tb);
        a = 0; b = 0; c = 0; d = 0;
        #20;
        a = 0; b = 0; c = 0; d = 1;
        #20;
        a = 0; b = 0; c = 1; d = 0;
        #20;
        a = 0; b = 0; c = 1; d = 1;
        #20;
        a = 0; b = 1; c = 0; d = 0;
        #20;
        a = 0; b = 1; c = 0; d = 1;
        #20;
        a = 0; b = 1; c = 1; d = 0;
        #20;
        a = 0; b = 1; c = 1; d = 1;
        #20;
        a = 1; b = 0; c = 0; d = 0;
        #20;
        a = 1; b = 0; c = 0; d = 1;
        #20;
        a = 1; b = 0; c = 1; d = 0;
        #20;
        a = 1; b = 0; c = 1; d = 1;
        #20;
        a = 1; b = 1; c = 0; d = 0;
        #20;
        a = 1; b = 1; c = 0; d = 1;
        #20;
        a = 1; b = 1; c = 1; d = 0;
        #20;
        a = 1; b = 1; c = 1; d = 1;
        #20;
        $display("Complete");
end

endmodule

Lab4/Q4/q4_tb.vcd
$date
	Sat Sep 17 15:19:32 2022
$end
$version
	Icarus Verilog
$end
$timescale
	1ns
$end
$scope module Q4_tb $end
$var wire 1 ! f $end
$var reg 1 " a $end
$var reg 1 # b $end
$var reg 1 $ c $end
$var reg 1 % d $end
$scope module q4 $end
$var wire 1 " a $end
$var wire 1 # b $end
$var wire 1 $ c $end
$var wire 1 % d $end
$var wire 1 ! f $end
$var wire 1 & f1 $end
$var wire 1 ' na $end
$var wire 1 ( nc $end
$var wire 1 ) nd $end
$upscope $end
$upscope $end
$enddefinitions $end
#0
$dumpvars
1)
1(
1'
0&
0%
0$
0#
0"
0!
$end
#20
1!
0)
1%
#40
0!
1)
0(
0%
1$
#60
1!
0)
1%
#80
0!
1)
1(
0%
0$
1#
#100
1!
0)
1%
#120
0!
1)
0(
0%
1$
#140
1!
0)
1%
#160
0!
1)
1(
0'
0%
0$
0#
1"
#180
1!
0)
1%
#200
0!
1&
1)
0(
0%
1$
#220
0)
1%
#240
0&
1)
1(
0%
0$
1#
#260
1!
0)
1%
#280
0!
1&
1)
0(
0%
1$
#300
0)
1%
