Lab6/Q1/dec3to8.v
module dec3to8(en,inp,y);
input en;
input [2:0]inp;
output reg [7:0]y;
integer i;
always@(en,inp)
	begin
		if(en==1)
			begin
			for(i=0;i<=7;i=i+1)
				begin
					if(inp == i)
					y[i] = 1;
					else
					y[i] =0;
				end
			end
		else y=8'b00000000;
	end
endmodule

Lab5/Q2/dec3to8_tb.v
`timescale 1ns/1ns
`include "dec3to8.v"
module dec3to8_tb();
reg en;
reg [2:0]inp;
wire [7:0]y;
dec3to8 d(en,inp,y);
initial
begin 
		$dumpfile("dec3to8_tb.vcd");
        $dumpvars(0,dec3to8_tb);
        en=1;
        inp[2] = 0; inp[1] = 0;inp[0] = 0; 
        #20;
        inp[2] = 0; inp[1] = 0;inp[0] = 1; 
        #20;
        inp[2] = 0; inp[1] = 1; inp[0] = 0;
        #20;
        inp[2] = 0; inp[1] = 1;inp[0] = 1; 
        #20;
        inp[2] = 1; inp[1] = 0; inp[0] = 0;
        #20;
        inp[2] = 1; inp[1] = 0; inp[0] = 1;
        #20;
        inp[2] = 1; inp[1] = 1; inp[0] = 0;
        #20;
        inp[2] = 1; inp[1] = 1; inp[0] = 1;
        #20;
        $display("Complete");
end

endmodule

Lab5/Q2/dec3to8_tb.vcd
$date
	Sat Oct  1 15:36:05 2022
$end
$version
	Icarus Verilog
$end
$timescale
	1ns
$end
$scope module dec3to8_tb $end
$var wire 8 ! y [7:0] $end
$var reg 1 " en $end
$var reg 3 # inp [2:0] $end
$scope module d $end
$var wire 1 " en $end
$var wire 3 $ inp [2:0] $end
$var reg 8 % y [7:0] $end
$var integer 32 & i [31:0] $end
$upscope $end
$upscope $end
$enddefinitions $end
#0
$dumpvars
b1000 &
b1 %
b0 $
b0 #
1"
b1 !
$end
#20
b10 !
b10 %
b1000 &
b1 #
b1 $
#40
b100 !
b100 %
b1000 &
b10 #
b10 $
#60
b1000 !
b1000 %
b1000 &
b11 #
b11 $
#80
b10000 !
b10000 %
b1000 &
b100 #
b100 $
#100
b100000 !
b100000 %
b1000 &
b101 #
b101 $
#120
b1000000 !
b1000000 %
b1000 &
b110 #
b110 $
#140
b10000000 !
b10000000 %
b1000 &
b111 #
b111 $
