Lab6/Q4/dec2to4.v
module dec2to4(en,a,b,y);
	input en,a,b;
	output reg [3:0]y;
   always @(en,a,b)
     begin
       if(en==1)
         begin
           if(a==0 & b==0) y=4'b0001;
           else if(a==0 & b==1) y=4'b0010;
           else if(a==1 & b==0) y=4'b0100;
           else if(a==1 & b==1) y=4'b1000;
         end
       else
        y=4'b0000;
     end
endmodule

Lab6/Q4/dec3to8.v
`include "dec2to4.v"
module dec3to8(a,b,c,y);
input a,b,c;
wire d;
output [7:0]y;
assign d=~a;
dec2to4 one(d,b,c,y[3:0]);
dec2to4 two(a,b,c,y[7:4]);
endmodule

Lab6/Q4/Q4.v
`include "dec3to8.v"
module Q4(s,i,y);
input [2:0]s;
input [7:0]i;
wire [7:0] temp;
output reg y;
dec3to8 um(s[2],s[1],s[0], temp);
always @(i)
begin 
if(temp[s]!=0)
assign y = 1'b1;
else 
assign y =1'b0;
end
endmodule

Lab6/Q4/Q4_tb.v
`timescale 1ns/1ns
`include "Q4.v"
module Q4_tb();
reg [2:0] inp;
reg [7:0]eh;
wire y;
Q4 q(inp,eh, y);
integer i;
initial
begin 
		$dumpfile("Q4_tb.vcd");
        $dumpvars(0,Q4_tb);
        eh = 8'b11010001;
        for(i=0; i<8; i=i+1) 
         begin
            inp = i; #20; 
            end
        $display("Complete");
end

endmodule

Lab6/Q4/Q4_tb.vcd
$date
	Sat Oct  8 16:50:45 2022
$end
$version
	Icarus Verilog
$end
$timescale
	1ns
$end
$scope module Q4_tb $end
$var wire 1 ! y $end
$var reg 8 " eh [7:0] $end
$var reg 3 # inp [2:0] $end
$var integer 32 $ i [31:0] $end
$scope module q $end
$var wire 8 % i [7:0] $end
$var wire 3 & s [2:0] $end
$var wire 8 ' temp [7:0] $end
$var reg 1 ! y $end
$scope module um $end
$var wire 1 ( a $end
$var wire 1 ) b $end
$var wire 1 * c $end
$var wire 1 + d $end
$var wire 8 , y [7:0] $end
$scope module one $end
$var wire 1 ) a $end
$var wire 1 * b $end
$var wire 1 + en $end
$var reg 4 - y [3:0] $end
$upscope $end
$scope module two $end
$var wire 1 ) a $end
$var wire 1 * b $end
$var wire 1 ( en $end
$var reg 4 . y [3:0] $end
$upscope $end
$upscope $end
$upscope $end
$upscope $end
$enddefinitions $end
#0
$dumpvars
b0 .
b1 -
b1 ,
1+
0*
0)
0(
b1 '
b0 &
b11010001 %
b0 $
b0 #
b11010001 "
0!
$end
#20
b10 '
b10 ,
b10 -
1*
b1 #
b1 &
b1 $
#40
b100 '
b100 ,
b100 -
1)
0*
b10 #
b10 &
b10 $
#60
b1000 '
b1000 ,
b1000 -
1*
b11 #
b11 &
b11 $
#80
0+
b0 -
b10000 '
b10000 ,
b1 .
1(
0)
0*
b100 #
b100 &
b100 $
#100
b100000 '
b100000 ,
b10 .
1*
b101 #
b101 &
b101 $
#120
b1000000 '
b1000000 ,
b100 .
1)
0*
b110 #
b110 &
b110 $
#140
b10000000 '
b10000000 ,
b1000 .
1*
b111 #
b111 &
b111 $
#160
b1000 $
