Lab3/Q3/Q3.v
module Q3(a,b,c,d,f);
	input a,b,c,d;
	output f;
	assign f = (b&c&d)|(a&c&d)|(a&b&d)|(a&b&c);
endmodule

Q3/Q3_tb.v
`timescale 1ns/1ns
`include "Q3.v"
module Q3_tb();
reg a,b,c,d;
wire f;
Q3 q3(a,b,c,d,f);
initial
begin 
		$dumpfile("q3_tb.vcd");
        $dumpvars(0,Q3_tb);
        a = 0; b = 0; c = 0; d = 0;
        #20;
        a = 0; b = 0; c = 0; d = 1;
        #20;
        a = 0; b = 0; c = 1; d = 0;
        #20;
        a = 0; b = 0; c = 1; d = 1;
        #20;
        a = 0; b = 1; c = 0; d = 0;
        #20;
        a = 0; b = 1; c = 0; d = 1;
        #20;
        a = 0; b = 1; c = 1; d = 0;
        #20;
        a = 0; b = 1; c = 1; d = 1;
        #20;
        a = 1; b = 0; c = 0; d = 0;
        #20;
        a = 1; b = 0; c = 0; d = 1;
        #20;
        a = 1; b = 0; c = 1; d = 0;
        #20;
        a = 1; b = 0; c = 1; d = 1;
        #20;
        a = 1; b = 1; c = 0; d = 0;
        #20;
        a = 1; b = 1; c = 0; d = 1;
        #20;
        a = 1; b = 1; c = 1; d = 0;
        #20;
        a = 1; b = 1; c = 1; d = 1;
        #20;
        $display("Complete");
end

endmodule

Lab3/Q3/q3_tb.vcd
$date
	Sat Sep 10 15:15:10 2022
$end
$version
	Icarus Verilog
$end
$timescale
	1ns
$end
$scope module Q3_tb $end
$var wire 1 ! f $end
$var reg 1 " a $end
$var reg 1 # b $end
$var reg 1 $ c $end
$var reg 1 % d $end
$scope module q3 $end
$var wire 1 " a $end
$var wire 1 # b $end
$var wire 1 $ c $end
$var wire 1 % d $end
$var wire 1 ! f $end
$upscope $end
$upscope $end
$enddefinitions $end
#0
$dumpvars
0%
0$
0#
0"
0!
$end
#20
1%
#40
0%
1$
#60
1%
#80
0%
0$
1#
#100
1%
#120
0%
1$
#140
1!
1%
#160
0!
0%
0$
0#
1"
#180
1%
#200
0%
1$
#220
1!
1%
#240
0!
0%
0$
1#
#260
1!
1%
#280
0%
1$
#300
1%
