Lab6/encoder/encoder.v
//Wite behavioural verilog code for 8 to 3
module penc8to3(inp,y);
  input [7:0]inp;
  output reg [2:0]y;
  always @(inp)
  begin
        if(inp[7]==1) y=3'b111;
        else if(inp[6]==1) y=3'b110;
        else if(inp[5]==1) y=3'b101;
        else if(inp[4]==1) y=3'b100;
        else if(inp[3]==1) y=3'b011;
        else if(inp[2]==1) y=3'b010;
        else if(inp[1]==1) y=3'b001;
        else
        y=3'b000;
  end
endmodule

Lab6/encoder/encoder_tb.v
`timescale 1ns/1ns
`include "encoder.v"
module encoder_tb();
reg [7:0] inp;
wire [2:0]y;
penc8to3 q(inp,y);
integer i;
initial
begin 
		$dumpfile("encoder_tb.vcd");
        $dumpvars(0,encoder_tb);
        for(i=0; i<8; i=i+1) 
         begin
         inp =0;
            inp[i] = 1; #20; 
            end
        $display("Complete");
end

endmodule

Lab6/encoder/encoder_tb.vcd
$date
	Sat Oct  8 16:21:57 2022
$end
$version
	Icarus Verilog
$end
$timescale
	1ns
$end
$scope module encoder_tb $end
$var wire 3 ! y [2:0] $end
$var reg 8 " inp [7:0] $end
$var integer 32 # i [31:0] $end
$scope module q $end
$var wire 8 $ inp [7:0] $end
$var reg 3 % y [2:0] $end
$upscope $end
$upscope $end
$enddefinitions $end
#0
$dumpvars
b0 %
b1 $
b0 #
b1 "
b0 !
$end
#20
b1 !
b1 %
b10 "
b10 $
b1 #
#40
b10 !
b10 %
b100 "
b100 $
b10 #
#60
b11 !
b11 %
b1000 "
b1000 $
b11 #
#80
b100 !
b100 %
b10000 "
b10000 $
b100 #
#100
b101 !
b101 %
b100000 "
b100000 $
b101 #
#120
b110 !
b110 %
b1000000 "
b1000000 $
b110 #
#140
b111 !
b111 %
b10000000 "
b10000000 $
b111 #
#160
b1000 #
